omniplate/__init__.py
omniplate/admin.py
omniplate/clogger.py
omniplate/correct_auto_bayesian.py
omniplate/corrections.py
omniplate/dilution_data_lucia.tsv
omniplate/dilution_data_xiao.tsv
omniplate/get_stats.py
omniplate/load_data.py
omniplate/manipulate_dfs.py
omniplate/midlog.py
omniplate/misc.py
omniplate/omcheck.py
omniplate/omerrors.py
omniplate/omfitderiv.py
omniplate/omgenutils.py
omniplate/ominfo.py
omniplate/omio.py
omniplate/omparallel.py
omniplate/omplot.py
omniplate/omstats.py
omniplate/omwells.py
omniplate/parse_plate.py
omniplate/parse_sunrise.py
omniplate/parse_tecan.py
omniplate/platereader.py
omniplate/promoter_activity.py
omniplate/sunder.py
omniplate-3.0.22.dist-info/METADATA
omniplate-3.0.22.dist-info/WHEEL
omniplate-3.0.22.dist-info/RECORD
